wotan/__init__.py
wotan/cofiam.py
wotan/constants.py
wotan/flatten.py
wotan/gaps.py
wotan/gp.py
wotan/helpers.py
wotan/huber_spline.py
wotan/iter_spline.py
wotan/location_estimates.py
wotan/lowess.py
wotan/norms.py
wotan/pspline.py
wotan/regression.py
wotan/slide_clipper.py
wotan/slider.py
wotan/t14.py
wotan/tests.py
wotan/version.py
wotan-1.10.dist-info/LICENSE
wotan-1.10.dist-info/METADATA
wotan-1.10.dist-info/WHEEL
wotan-1.10.dist-info/top_level.txt
wotan-1.10.dist-info/RECORD
