Metadata-Version: 2.1
Name: wotan
Version: 1.10
Summary: Detrending algorithms
Home-page: https://github.com/hippke/wotan
Author: Michael Hippke
Author-email: michael@hippke.org
License: MIT
Platform: UNKNOWN
Requires-Dist: numpy
Requires-Dist: numba
Requires-Dist: scipy
